google_drive/__init__.py
google_drive/google_calendar.py
google_drive/google_docs.py
google_drive/conf/locale/config.yaml
google_drive/public/css/google_calendar.css
google_drive/public/css/google_docs.css
google_drive/public/css/google_edit.css
google_drive/public/js/google_calendar.js
google_drive/public/js/google_calendar_edit.js
google_drive/public/js/google_docs.js
google_drive/public/js/google_docs_edit.js
google_drive/templates/html/google_calendar.html
google_drive/templates/html/google_calendar_edit.html
google_drive/templates/html/google_docs.html
google_drive/templates/html/google_docs_edit.html
google_drive/translations/config.yaml
xblock_google_drive-0.8.1.dist-info/licenses/LICENSE
xblock_google_drive-0.8.1.dist-info/METADATA
xblock_google_drive-0.8.1.dist-info/WHEEL
xblock_google_drive-0.8.1.dist-info/entry_points.txt
xblock_google_drive-0.8.1.dist-info/top_level.txt
xblock_google_drive-0.8.1.dist-info/RECORD
