Metadata-Version: 2.4
Name: xblock-google-drive
Version: 0.8.1
Summary: An XBlock which allows embedding of Google documents and calendar within an edX course
Home-page: https://github.com/openedx/xblock-google-drive
Classifier: Programming Language :: Python
Classifier: Programming Language :: Python :: 3.11
Classifier: Programming Language :: Python :: 3.12
Classifier: Framework :: Django
Classifier: Framework :: Django :: 4.2
Classifier: Framework :: Django :: 5.2
Requires-Python: >=3.11
License-File: LICENSE
Requires-Dist: Django
Requires-Dist: XBlock[django]
Requires-Dist: requests
Dynamic: classifier
Dynamic: description
Dynamic: description-content-type
Dynamic: home-page
Dynamic: license-file
Dynamic: requires-dist
Dynamic: requires-python
Dynamic: summary
